MANIFEST.in
README.rst
setup.py
aliyun_python_sdk_acs.egg-info/PKG-INFO
aliyun_python_sdk_acs.egg-info/SOURCES.txt
aliyun_python_sdk_acs.egg-info/dependency_links.txt
aliyun_python_sdk_acs.egg-info/requires.txt
aliyun_python_sdk_acs.egg-info/top_level.txt
aliyunsdkacs/__init__.py
aliyunsdkacs/request/__init__.py
aliyunsdkacs/request/v20150101/DeleteApiRequest.py
aliyunsdkacs/request/v20150101/DeleteControlPolicyRequest.py
aliyunsdkacs/request/v20150101/DeleteFlowControlRequest.py
aliyunsdkacs/request/v20150101/DeletePolicyRequest.py
aliyunsdkacs/request/v20150101/DeleteProductRequest.py
aliyunsdkacs/request/v20150101/DeleteTairCacheRequest.py
aliyunsdkacs/request/v20150101/DeleteVersionRequest.py
aliyunsdkacs/request/v20150101/GetApiBackupListRequest.py
aliyunsdkacs/request/v20150101/GetApiBackupRequest.py
aliyunsdkacs/request/v20150101/GetApiNewRequest.py
aliyunsdkacs/request/v20150101/GetApiRequest.py
aliyunsdkacs/request/v20150101/GetControlPolicyRequest.py
aliyunsdkacs/request/v20150101/GetGlobalRequest.py
aliyunsdkacs/request/v20150101/GetProductRequest.py
aliyunsdkacs/request/v20150101/GetTairCacheRequest.py
aliyunsdkacs/request/v20150101/GetVersionRequest.py
aliyunsdkacs/request/v20150101/PutApiErrorMappingRequest.py
aliyunsdkacs/request/v20150101/PutApiNewRequest.py
aliyunsdkacs/request/v20150101/PutApiParametersRequest.py
aliyunsdkacs/request/v20150101/PutApiReleaseRequest.py
aliyunsdkacs/request/v20150101/PutApiRequest.py
aliyunsdkacs/request/v20150101/PutApiResultMappingRequest.py
aliyunsdkacs/request/v20150101/PutApiRollbackRequest.py
aliyunsdkacs/request/v20150101/PutApiStatusRequest.py
aliyunsdkacs/request/v20150101/PutApiVisibilityRequest.py
aliyunsdkacs/request/v20150101/PutControlPolicyRequest.py
aliyunsdkacs/request/v20150101/PutFlowControlRequest.py
aliyunsdkacs/request/v20150101/PutGlobalErrorMappingRequest.py
aliyunsdkacs/request/v20150101/PutPolicyRequest.py
aliyunsdkacs/request/v20150101/PutProductRequest.py
aliyunsdkacs/request/v20150101/PutVersionErrorMappingRequest.py
aliyunsdkacs/request/v20150101/PutVersionParametersRequest.py
aliyunsdkacs/request/v20150101/PutVersionRequest.py
aliyunsdkacs/request/v20150101/__init__.py
