Metadata-Version: 1.1
Name: aliyun-python-sdk-acs
Version: 0.0.2
Summary: The acs module of Aliyun Python sdk.
Home-page: http://develop.aliyun.com/sdk/python
Author: Aliyun
Author-email: aliyun-developers-efficiency@list.alibaba-inc.com
License: Apache
Keywords: aliyun,sdk,acs
Platform: any
Classifier: Development Status :: 4 - Beta
Classifier: Intended Audience :: Developers
Classifier: License :: OSI Approved :: Apache Software License
Classifier: Programming Language :: Python
Classifier: Programming Language :: Python :: 2.6
Classifier: Programming Language :: Python :: 2.7
Classifier: Programming Language :: Python :: 3
Classifier: Programming Language :: Python :: 3.3
Classifier: Topic :: Software Development
